{
  "documentVersion": "1.0",
  "layout": {
    "fontFamily": "Carlito",
    "fontSize": 11.4,
    "lineHeight": 1.7,
    "pageSize": "A4",
    "margins": {
      "top": 86,
      "right": 74,
      "bottom": 88,
      "left": 74
    },
    "hyphenation": "soft",
    "justifyEngine": "advanced",
    "justifyStrategy": "auto"
  },
  "styles": {
    "heading-1": {
      "fontFamily": "Caladea",
      "fontSize": 27,
      "lineHeight": 1.18,
      "color": "#1c2430",
      "textAlign": "center",
      "hyphenation": "off",
      "marginTop": 18,
      "marginBottom": 22,
      "letterSpacing": 0.2,
      "keepWithNext": true
    },
    "heading-2": {
      "fontFamily": "Carlito",
      "fontSize": 13.6,
      "fontWeight": 700,
      "color": "#1f3f68",
      "hyphenation": "off",
      "borderBottomWidth": 0.7,
      "borderBottomColor": "#cad5e5",
      "paddingBottom": 2,
      "marginTop": 20,
      "marginBottom": 10.5,
      "keepWithNext": true
    },
    "heading-3": {
      "fontFamily": "Carlito",
      "fontSize": 11.6,
      "fontWeight": 700,
      "color": "#2f547f",
      "hyphenation": "off",
      "marginTop": 9,
      "marginBottom": 7.5,
      "keepWithNext": true
    },
    "paragraph": {
      "textAlign": "left",
      "hyphenation": "soft",
      "lineHeight": 1.74,
      "marginBottom": 11.8
    },
    "blockquote": {
      "textAlign": "left",
      "hyphenation": "off",
      "fontFamily": "Caladea",
      "fontStyle": "italic",
      "fontSize": 12.2,
      "lineHeight": 1.58,
      "color": "#2a3240",
      "backgroundColor": "#f6f8fc",
      "borderLeftWidth": 2.2,
      "borderLeftColor": "#9eacc4",
      "paddingLeft": 15,
      "paddingRight": 11,
      "paddingTop": 7,
      "paddingBottom": 7,
      "marginTop": 4.5,
      "marginBottom": 15
    },
    "blockquote-attribution": {
      "textAlign": "right",
      "fontFamily": "Carlito",
      "fontSize": 9.6,
      "color": "#677488",
      "marginTop": 2,
      "marginBottom": 8
    },
    "inline-code": {
      "fontFamily": "Cousine",
      "fontSize": 9.7,
      "color": "#173657",
      "backgroundColor": "#eef3f8",
      "borderRadius": 2
    },
    "code-block": {
      "fontFamily": "Cousine",
      "fontSize": 9.9,
      "lineHeight": 1.39,
      "allowLineSplit": true,
      "overflowPolicy": "clip",
      "color": "#172133",
      "backgroundColor": "#f2f6fb",
      "borderWidth": 1,
      "borderColor": "#c7d2e3",
      "borderRadius": 5,
      "paddingTop": 10,
      "paddingBottom": 10,
      "paddingLeft": 12,
      "paddingRight": 12,
      "marginTop": 2,
      "marginBottom": 15
    },
    "table-cell": {
      "fontFamily": "Carlito",
      "paddingTop": 5.5,
      "paddingBottom": 5.5,
      "paddingLeft": 6,
      "paddingRight": 6,
      "borderWidth": 0.6,
      "borderColor": "#c6d0df"
    },
    "thematic-break": {
      "width": 154,
      "borderTopWidth": 0.8,
      "borderTopColor": "#9eabc0",
      "marginTop": 17,
      "marginBottom": 21
    },
    "footnotes-heading": {
      "fontFamily": "Carlito",
      "fontWeight": 700
    },
    "footnotes-item": {
      "fontFamily": "Carlito"
    },
    "references-heading": {
      "fontFamily": "Carlito",
      "fontWeight": 700
    },
    "references-item": {
      "fontFamily": "Carlito"
    }
  },
  "elements": [
    {
      "type": "heading-1",
      "content": "",
      "children": [
        {
          "type": "text",
          "content": "draft2final For Humans: A Friendly Tutorial"
        }
      ],
      "properties": {
        "sourceRange": {
          "lineStart": 2,
          "colStart": 1,
          "lineEnd": 2,
          "colEnd": 46
        },
        "sourceSyntax": "h1"
      }
    },
    {
      "type": "paragraph",
      "content": "",
      "children": [
        {
          "type": "text",
          "content": "You write in plain Markdown. "
        },
        {
          "type": "text",
          "content": "draft2final",
          "properties": {
            "style": {
              "fontFamily": "Cousine",
              "fontSize": 9.7,
              "color": "#173657",
              "backgroundColor": "#eef3f8",
              "borderRadius": 2
            }
          }
        },
        {
          "type": "text",
          "content": " helps that writing become real, polished documents fast."
        }
      ],
      "properties": {
        "sourceRange": {
          "lineStart": 4,
          "colStart": 1,
          "lineEnd": 4,
          "colEnd": 100
        },
        "sourceSyntax": "paragraph",
        "dropCap": {
          "enabled": true,
          "lines": 4,
          "gap": 6,
          "characterStyle": {
            "fontFamily": "Caladea",
            "fontWeight": 700,
            "color": "#1f3550"
          }
        }
      }
    },
    {
      "type": "paragraph",
      "content": "",
      "children": [
        {
          "type": "text",
          "content": "This guide is for writers, directors, researchers, students, and anyone who wants clean output without wrestling complex layout tools."
        }
      ],
      "properties": {
        "sourceRange": {
          "lineStart": 6,
          "colStart": 1,
          "lineEnd": 6,
          "colEnd": 135
        },
        "sourceSyntax": "paragraph"
      }
    },
    {
      "type": "heading-2",
      "content": "",
      "children": [
        {
          "type": "text",
          "content": "Who This Is For"
        }
      ],
      "properties": {
        "sourceRange": {
          "lineStart": 8,
          "colStart": 1,
          "lineEnd": 8,
          "colEnd": 19
        },
        "sourceSyntax": "h2"
      }
    },
    {
      "type": "list-item-unordered-0",
      "content": "",
      "children": [
        {
          "type": "text",
          "content": "• "
        },
        {
          "type": "text",
          "content": "Novelist: You want to stay in writing flow, then generate manuscript-ready output without format panic."
        }
      ],
      "properties": {
        "sourceRange": {
          "lineStart": 10,
          "colStart": 1,
          "lineEnd": 10,
          "colEnd": 106
        },
        "sourceSyntax": "listItem"
      }
    },
    {
      "type": "list-item-unordered-0",
      "content": "",
      "children": [
        {
          "type": "text",
          "content": "• "
        },
        {
          "type": "text",
          "content": "Screenwriter or director: You want plain-text drafting speed and screenplay-style output when it is time to share."
        }
      ],
      "properties": {
        "sourceRange": {
          "lineStart": 11,
          "colStart": 1,
          "lineEnd": 11,
          "colEnd": 117
        },
        "sourceSyntax": "listItem"
      }
    },
    {
      "type": "list-item-unordered-0",
      "content": "",
      "children": [
        {
          "type": "text",
          "content": "• "
        },
        {
          "type": "text",
          "content": "Student or academic: You want to focus on argument and structure first, then produce clean, professional documents on demand."
        }
      ],
      "properties": {
        "sourceRange": {
          "lineStart": 12,
          "colStart": 1,
          "lineEnd": 12,
          "colEnd": 128
        },
        "sourceSyntax": "listItem"
      }
    },
    {
      "type": "paragraph",
      "content": "",
      "children": [
        {
          "type": "text",
          "content": "Before tools like this, many people did the same painful dance:"
        }
      ],
      "properties": {
        "sourceRange": {
          "lineStart": 14,
          "colStart": 1,
          "lineEnd": 14,
          "colEnd": 64
        },
        "sourceSyntax": "paragraph",
        "keepWithNext": true
      }
    },
    {
      "type": "list-item-unordered-0",
      "content": "",
      "children": [
        {
          "type": "text",
          "content": "• "
        },
        {
          "type": "text",
          "content": "Write in one place"
        }
      ],
      "properties": {
        "sourceRange": {
          "lineStart": 16,
          "colStart": 1,
          "lineEnd": 16,
          "colEnd": 21
        },
        "sourceSyntax": "listItem"
      }
    },
    {
      "type": "list-item-unordered-0",
      "content": "",
      "children": [
        {
          "type": "text",
          "content": "• "
        },
        {
          "type": "text",
          "content": "Reformat by hand in another"
        }
      ],
      "properties": {
        "sourceRange": {
          "lineStart": 17,
          "colStart": 1,
          "lineEnd": 17,
          "colEnd": 30
        },
        "sourceSyntax": "listItem"
      }
    },
    {
      "type": "list-item-unordered-0",
      "content": "",
      "children": [
        {
          "type": "text",
          "content": "• "
        },
        {
          "type": "text",
          "content": "Lose hours fixing layout details"
        }
      ],
      "properties": {
        "sourceRange": {
          "lineStart": 18,
          "colStart": 1,
          "lineEnd": 18,
          "colEnd": 35
        },
        "sourceSyntax": "listItem"
      }
    },
    {
      "type": "list-item-unordered-0",
      "content": "",
      "children": [
        {
          "type": "text",
          "content": "• "
        },
        {
          "type": "text",
          "content": "Stress about submission rules and avoidable rejections"
        }
      ],
      "properties": {
        "sourceRange": {
          "lineStart": 19,
          "colStart": 1,
          "lineEnd": 19,
          "colEnd": 57
        },
        "sourceSyntax": "listItem"
      }
    },
    {
      "type": "paragraph",
      "content": "",
      "children": [
        {
          "type": "text",
          "content": "Now the workflow can be:"
        }
      ],
      "properties": {
        "sourceRange": {
          "lineStart": 21,
          "colStart": 1,
          "lineEnd": 21,
          "colEnd": 25
        },
        "sourceSyntax": "paragraph",
        "keepWithNext": true
      }
    },
    {
      "type": "list-item-unordered-0",
      "content": "",
      "children": [
        {
          "type": "text",
          "content": "• "
        },
        {
          "type": "text",
          "content": "Focus on ideas first"
        }
      ],
      "properties": {
        "sourceRange": {
          "lineStart": 23,
          "colStart": 1,
          "lineEnd": 23,
          "colEnd": 23
        },
        "sourceSyntax": "listItem"
      }
    },
    {
      "type": "list-item-unordered-0",
      "content": "",
      "children": [
        {
          "type": "text",
          "content": "• "
        },
        {
          "type": "text",
          "content": "Keep writing in plain text"
        }
      ],
      "properties": {
        "sourceRange": {
          "lineStart": 24,
          "colStart": 1,
          "lineEnd": 24,
          "colEnd": 29
        },
        "sourceSyntax": "listItem"
      }
    },
    {
      "type": "list-item-unordered-0",
      "content": "",
      "children": [
        {
          "type": "text",
          "content": "• "
        },
        {
          "type": "text",
          "content": "Generate the right format on demand"
        }
      ],
      "properties": {
        "sourceRange": {
          "lineStart": 25,
          "colStart": 1,
          "lineEnd": 25,
          "colEnd": 38
        },
        "sourceSyntax": "listItem"
      }
    },
    {
      "type": "paragraph",
      "content": "",
      "children": [
        {
          "type": "text",
          "content": "In one sitting, you will:"
        }
      ],
      "properties": {
        "sourceRange": {
          "lineStart": 27,
          "colStart": 1,
          "lineEnd": 27,
          "colEnd": 26
        },
        "sourceSyntax": "paragraph",
        "keepWithNext": true
      }
    },
    {
      "type": "list-item-ordered-0",
      "content": "",
      "children": [
        {
          "type": "text",
          "content": "I.  "
        },
        {
          "type": "text",
          "content": "Write a technical manual"
        }
      ],
      "properties": {
        "sourceRange": {
          "lineStart": 29,
          "colStart": 1,
          "lineEnd": 29,
          "colEnd": 28
        },
        "sourceSyntax": "listItem"
      }
    },
    {
      "type": "list-item-ordered-0",
      "content": "",
      "children": [
        {
          "type": "text",
          "content": "II.  "
        },
        {
          "type": "text",
          "content": "Write a screenplay"
        }
      ],
      "properties": {
        "sourceRange": {
          "lineStart": 30,
          "colStart": 1,
          "lineEnd": 30,
          "colEnd": 22
        },
        "sourceSyntax": "listItem"
      }
    },
    {
      "type": "list-item-ordered-0",
      "content": "",
      "children": [
        {
          "type": "text",
          "content": "III.  "
        },
        {
          "type": "text",
          "content": "Write a manuscript"
        }
      ],
      "properties": {
        "sourceRange": {
          "lineStart": 31,
          "colStart": 1,
          "lineEnd": 31,
          "colEnd": 22
        },
        "sourceSyntax": "listItem"
      }
    },
    {
      "type": "list-item-ordered-0",
      "content": "",
      "children": [
        {
          "type": "text",
          "content": "IV.  "
        },
        {
          "type": "text",
          "content": "Remix formats for fun (and insight)"
        }
      ],
      "properties": {
        "sourceRange": {
          "lineStart": 32,
          "colStart": 1,
          "lineEnd": 32,
          "colEnd": 39
        },
        "sourceSyntax": "listItem"
      }
    },
    {
      "type": "paragraph",
      "content": "",
      "children": [
        {
          "type": "text",
          "content": "You can copy and paste every command."
        }
      ],
      "properties": {
        "sourceRange": {
          "lineStart": 34,
          "colStart": 1,
          "lineEnd": 34,
          "colEnd": 38
        },
        "sourceSyntax": "paragraph"
      }
    },
    {
      "type": "heading-2",
      "content": "",
      "children": [
        {
          "type": "text",
          "content": "First, One Minute Setup"
        }
      ],
      "properties": {
        "sourceRange": {
          "lineStart": 36,
          "colStart": 1,
          "lineEnd": 36,
          "colEnd": 27
        },
        "sourceSyntax": "h2"
      }
    },
    {
      "type": "paragraph",
      "content": "",
      "children": [
        {
          "type": "text",
          "content": "From repo root:"
        }
      ],
      "properties": {
        "sourceRange": {
          "lineStart": 38,
          "colStart": 1,
          "lineEnd": 38,
          "colEnd": 16
        },
        "sourceSyntax": "paragraph",
        "keepWithNext": true
      }
    },
    {
      "type": "code-block",
      "content": "npm install\nnpm run dev —prefix draft2final — —help",
      "properties": {
        "sourceRange": {
          "lineStart": 40,
          "colStart": 1,
          "lineEnd": 43,
          "colEnd": 4
        },
        "sourceSyntax": "codeFence",
        "language": "bash"
      }
    },
    {
      "type": "paragraph",
      "content": "",
      "children": [
        {
          "type": "text",
          "content": "What you should see:"
        }
      ],
      "properties": {
        "sourceRange": {
          "lineStart": 45,
          "colStart": 1,
          "lineEnd": 45,
          "colEnd": 21
        },
        "sourceSyntax": "paragraph",
        "keepWithNext": true
      }
    },
    {
      "type": "list-item-unordered-0",
      "content": "",
      "children": [
        {
          "type": "text",
          "content": "• "
        },
        {
          "type": "text",
          "content": "A help output from "
        },
        {
          "type": "text",
          "content": "draft2final",
          "properties": {
            "style": {
              "fontFamily": "Cousine",
              "fontSize": 9.7,
              "color": "#173657",
              "backgroundColor": "#eef3f8",
              "borderRadius": 2
            }
          }
        },
        {
          "type": "text",
          "content": " with options like "
        },
        {
          "type": "text",
          "content": "--using",
          "properties": {
            "style": {
              "fontFamily": "Cousine",
              "fontSize": 9.7,
              "color": "#173657",
              "backgroundColor": "#eef3f8",
              "borderRadius": 2
            }
          }
        },
        {
          "type": "text",
          "content": ", "
        },
        {
          "type": "text",
          "content": "--theme",
          "properties": {
            "style": {
              "fontFamily": "Cousine",
              "fontSize": 9.7,
              "color": "#173657",
              "backgroundColor": "#eef3f8",
              "borderRadius": 2
            }
          }
        },
        {
          "type": "text",
          "content": ", and "
        },
        {
          "type": "text",
          "content": "--out",
          "properties": {
            "style": {
              "fontFamily": "Cousine",
              "fontSize": 9.7,
              "color": "#173657",
              "backgroundColor": "#eef3f8",
              "borderRadius": 2
            }
          }
        }
      ],
      "properties": {
        "sourceRange": {
          "lineStart": 47,
          "colStart": 1,
          "lineEnd": 47,
          "colEnd": 87
        },
        "sourceSyntax": "listItem"
      }
    },
    {
      "type": "paragraph",
      "content": "",
      "children": [
        {
          "type": "text",
          "content": "Create a folder for this tutorial:"
        }
      ],
      "properties": {
        "sourceRange": {
          "lineStart": 49,
          "colStart": 1,
          "lineEnd": 49,
          "colEnd": 35
        },
        "sourceSyntax": "paragraph",
        "keepWithNext": true
      }
    },
    {
      "type": "code-block",
      "content": "mkdir -p samples/tutorial",
      "properties": {
        "sourceRange": {
          "lineStart": 51,
          "colStart": 1,
          "lineEnd": 53,
          "colEnd": 4
        },
        "sourceSyntax": "codeFence",
        "language": "bash"
      }
    },
    {
      "type": "paragraph",
      "content": "",
      "children": [
        {
          "type": "text",
          "content": "PowerShell alternative:"
        }
      ],
      "properties": {
        "sourceRange": {
          "lineStart": 55,
          "colStart": 1,
          "lineEnd": 55,
          "colEnd": 24
        },
        "sourceSyntax": "paragraph",
        "keepWithNext": true
      }
    },
    {
      "type": "code-block",
      "content": "New-Item -ItemType Directory -Force -Path samples/tutorial",
      "properties": {
        "sourceRange": {
          "lineStart": 57,
          "colStart": 1,
          "lineEnd": 59,
          "colEnd": 4
        },
        "sourceSyntax": "codeFence",
        "language": "powershell"
      }
    },
    {
      "type": "heading-2",
      "content": "",
      "children": [
        {
          "type": "text",
          "content": "Part 1: Make a Technical Manual"
        }
      ],
      "properties": {
        "sourceRange": {
          "lineStart": 61,
          "colStart": 1,
          "lineEnd": 61,
          "colEnd": 35
        },
        "sourceSyntax": "h2"
      }
    },
    {
      "type": "paragraph",
      "content": "",
      "children": [
        {
          "type": "text",
          "content": "Create "
        },
        {
          "type": "text",
          "content": "samples/tutorial/tech-manual.md",
          "properties": {
            "style": {
              "fontFamily": "Cousine",
              "fontSize": 9.7,
              "color": "#173657",
              "backgroundColor": "#eef3f8",
              "borderRadius": 2
            }
          }
        },
        {
          "type": "text",
          "content": ":"
        }
      ],
      "properties": {
        "sourceRange": {
          "lineStart": 63,
          "colStart": 1,
          "lineEnd": 63,
          "colEnd": 42
        },
        "sourceSyntax": "paragraph",
        "keepWithNext": true
      }
    },
    {
      "type": "code-block",
      "content": "—\ntitle: “VMPrint Field Manual”\nauthor: “Alex Typesetter”\n—\n\n# VMPrint Field Manual\n\n## Why this exists\n\nPeople do serious work under pressure. Good docs reduce panic.\n\n## Install Checklist\n\n1. Install Node.js 18+\n2. Run `npm install`\n3. Run `npm run build`\n\n## Fast Recovery Rules\n\n- Commit before risky changes\n- Keep snapshots current\n- If layout shifts, inspect AST JSON first\n\n## One command to render\n\n`draft2final input.md —using mkd-mkd —out output.pdf`",
      "properties": {
        "sourceRange": {
          "lineStart": 65,
          "colStart": 1,
          "lineEnd": 92,
          "colEnd": 4
        },
        "sourceSyntax": "codeFence",
        "language": "md"
      }
    },
    {
      "type": "paragraph",
      "content": "",
      "children": [
        {
          "type": "text",
          "content": "Render it:"
        }
      ],
      "properties": {
        "sourceRange": {
          "lineStart": 94,
          "colStart": 1,
          "lineEnd": 94,
          "colEnd": 11
        },
        "sourceSyntax": "paragraph",
        "keepWithNext": true
      }
    },
    {
      "type": "code-block",
      "content": "npm run dev —prefix draft2final — samples/tutorial/tech-manual.md —using mkd-mkd —out samples/tutorial/tech-manual.pdf",
      "properties": {
        "sourceRange": {
          "lineStart": 96,
          "colStart": 1,
          "lineEnd": 98,
          "colEnd": 4
        },
        "sourceSyntax": "codeFence",
        "language": "bash"
      }
    },
    {
      "type": "paragraph",
      "content": "",
      "children": [
        {
          "type": "text",
          "content": "What you should see:"
        }
      ],
      "properties": {
        "sourceRange": {
          "lineStart": 100,
          "colStart": 1,
          "lineEnd": 100,
          "colEnd": 21
        },
        "sourceSyntax": "paragraph",
        "keepWithNext": true
      }
    },
    {
      "type": "list-item-unordered-0",
      "content": "",
      "children": [
        {
          "type": "text",
          "content": "• "
        },
        {
          "type": "text",
          "content": "A line like "
        },
        {
          "type": "text",
          "content": "[draft2final] Wrote ...tech-manual.pdf",
          "properties": {
            "style": {
              "fontFamily": "Cousine",
              "fontSize": 9.7,
              "color": "#173657",
              "backgroundColor": "#eef3f8",
              "borderRadius": 2
            }
          }
        }
      ],
      "properties": {
        "sourceRange": {
          "lineStart": 102,
          "colStart": 1,
          "lineEnd": 102,
          "colEnd": 55
        },
        "sourceSyntax": "listItem"
      }
    },
    {
      "type": "list-item-unordered-0",
      "content": "",
      "children": [
        {
          "type": "text",
          "content": "• "
        },
        {
          "type": "text",
          "content": "A new PDF at "
        },
        {
          "type": "text",
          "content": "samples/tutorial/tech-manual.pdf",
          "properties": {
            "style": {
              "fontFamily": "Cousine",
              "fontSize": 9.7,
              "color": "#173657",
              "backgroundColor": "#eef3f8",
              "borderRadius": 2
            }
          }
        }
      ],
      "properties": {
        "sourceRange": {
          "lineStart": 103,
          "colStart": 1,
          "lineEnd": 103,
          "colEnd": 50
        },
        "sourceSyntax": "listItem"
      }
    },
    {
      "type": "paragraph",
      "content": "",
      "children": [
        {
          "type": "text",
          "content": "Now try style variants:"
        }
      ],
      "properties": {
        "sourceRange": {
          "lineStart": 105,
          "colStart": 1,
          "lineEnd": 105,
          "colEnd": 24
        },
        "sourceSyntax": "paragraph",
        "keepWithNext": true
      }
    },
    {
      "type": "code-block",
      "content": "npm run dev —prefix draft2final — samples/tutorial/tech-manual.md —using mkd-mkd —theme novel —out samples/tutorial/tech-manual.novel.pdf\nnpm run dev —prefix draft2final — samples/tutorial/tech-manual.md —using mkd-mkd —theme opensource —out samples/tutorial/tech-manual.opensource.pdf",
      "properties": {
        "sourceRange": {
          "lineStart": 107,
          "colStart": 1,
          "lineEnd": 110,
          "colEnd": 4
        },
        "sourceSyntax": "codeFence",
        "language": "bash"
      }
    },
    {
      "type": "paragraph",
      "content": "",
      "children": [
        {
          "type": "text",
          "content": "Same words. Different personality."
        }
      ],
      "properties": {
        "sourceRange": {
          "lineStart": 112,
          "colStart": 1,
          "lineEnd": 112,
          "colEnd": 35
        },
        "sourceSyntax": "paragraph"
      }
    },
    {
      "type": "paragraph",
      "content": "",
      "children": [
        {
          "type": "text",
          "content": "This is one of the big unlocks: you can keep the content stable and change presentation per audience."
        }
      ],
      "properties": {
        "sourceRange": {
          "lineStart": 114,
          "colStart": 1,
          "lineEnd": 114,
          "colEnd": 102
        },
        "sourceSyntax": "paragraph"
      }
    },
    {
      "type": "heading-2",
      "content": "",
      "children": [
        {
          "type": "text",
          "content": "Part 2: Make a Screenplay"
        }
      ],
      "properties": {
        "sourceRange": {
          "lineStart": 116,
          "colStart": 1,
          "lineEnd": 116,
          "colEnd": 29
        },
        "sourceSyntax": "h2"
      }
    },
    {
      "type": "paragraph",
      "content": "",
      "children": [
        {
          "type": "text",
          "content": "Create "
        },
        {
          "type": "text",
          "content": "samples/tutorial/screenplay.md",
          "properties": {
            "style": {
              "fontFamily": "Cousine",
              "fontSize": 9.7,
              "color": "#173657",
              "backgroundColor": "#eef3f8",
              "borderRadius": 2
            }
          }
        },
        {
          "type": "text",
          "content": ":"
        }
      ],
      "properties": {
        "sourceRange": {
          "lineStart": 118,
          "colStart": 1,
          "lineEnd": 118,
          "colEnd": 41
        },
        "sourceSyntax": "paragraph",
        "keepWithNext": true
      }
    },
    {
      "type": "code-block",
      "content": "—\ntitle: “THE LAYOUT HEIST”\nauthor: “A. Typesetter”\n—\n\nINT. BUILD ROOM - NIGHT\n\nRows of monitors. One progress bar. No mercy.\n\nNOVA\n(low)\nIf pagination slips, we lose the morning.\n\nRHEA\nThen we don’t slip.\n\nThe printer wakes up like a jet engine.\n\nNOVA\nPrint it.",
      "properties": {
        "sourceRange": {
          "lineStart": 120,
          "colStart": 1,
          "lineEnd": 141,
          "colEnd": 4
        },
        "sourceSyntax": "codeFence",
        "language": "md"
      }
    },
    {
      "type": "paragraph",
      "content": "",
      "children": [
        {
          "type": "text",
          "content": "Render it:"
        }
      ],
      "properties": {
        "sourceRange": {
          "lineStart": 143,
          "colStart": 1,
          "lineEnd": 143,
          "colEnd": 11
        },
        "sourceSyntax": "paragraph",
        "keepWithNext": true
      }
    },
    {
      "type": "code-block",
      "content": "npm run dev —prefix draft2final — samples/tutorial/screenplay.md —using mkd-screenplay —out samples/tutorial/screenplay.pdf",
      "properties": {
        "sourceRange": {
          "lineStart": 145,
          "colStart": 1,
          "lineEnd": 147,
          "colEnd": 4
        },
        "sourceSyntax": "codeFence",
        "language": "bash"
      }
    },
    {
      "type": "paragraph",
      "content": "",
      "children": [
        {
          "type": "text",
          "content": "What you should see:"
        }
      ],
      "properties": {
        "sourceRange": {
          "lineStart": 149,
          "colStart": 1,
          "lineEnd": 149,
          "colEnd": 21
        },
        "sourceSyntax": "paragraph",
        "keepWithNext": true
      }
    },
    {
      "type": "list-item-unordered-0",
      "content": "",
      "children": [
        {
          "type": "text",
          "content": "• "
        },
        {
          "type": "text",
          "content": "A new screenplay PDF at "
        },
        {
          "type": "text",
          "content": "samples/tutorial/screenplay.pdf",
          "properties": {
            "style": {
              "fontFamily": "Cousine",
              "fontSize": 9.7,
              "color": "#173657",
              "backgroundColor": "#eef3f8",
              "borderRadius": 2
            }
          }
        }
      ],
      "properties": {
        "sourceRange": {
          "lineStart": 151,
          "colStart": 1,
          "lineEnd": 151,
          "colEnd": 60
        },
        "sourceSyntax": "listItem"
      }
    },
    {
      "type": "paragraph",
      "content": "",
      "children": [
        {
          "type": "text",
          "content": "If you are a filmmaker, this is the fun moment: plain text in, screenplay energy out."
        }
      ],
      "properties": {
        "sourceRange": {
          "lineStart": 153,
          "colStart": 1,
          "lineEnd": 153,
          "colEnd": 86
        },
        "sourceSyntax": "paragraph"
      }
    },
    {
      "type": "heading-2",
      "content": "",
      "children": [
        {
          "type": "text",
          "content": "Part 3: Make a Manuscript"
        }
      ],
      "properties": {
        "sourceRange": {
          "lineStart": 155,
          "colStart": 1,
          "lineEnd": 155,
          "colEnd": 29
        },
        "sourceSyntax": "h2"
      }
    },
    {
      "type": "paragraph",
      "content": "",
      "children": [
        {
          "type": "text",
          "content": "Create "
        },
        {
          "type": "text",
          "content": "samples/tutorial/manuscript.md",
          "properties": {
            "style": {
              "fontFamily": "Cousine",
              "fontSize": 9.7,
              "color": "#173657",
              "backgroundColor": "#eef3f8",
              "borderRadius": 2
            }
          }
        },
        {
          "type": "text",
          "content": ":"
        }
      ],
      "properties": {
        "sourceRange": {
          "lineStart": 157,
          "colStart": 1,
          "lineEnd": 157,
          "colEnd": 41
        },
        "sourceSyntax": "paragraph",
        "keepWithNext": true
      }
    },
    {
      "type": "code-block",
      "content": "—\ntitle: “The Last Typesetter”\nauthor: “Alex Writer”\n—\n\nChapter One\n\nThe cursor blinked in the dark room like it knew a secret.\n\nMira wrote one sentence, then another, then one she almost deleted.\nShe kept it. It was not perfect, but it was true.",
      "properties": {
        "sourceRange": {
          "lineStart": 159,
          "colStart": 1,
          "lineEnd": 171,
          "colEnd": 4
        },
        "sourceSyntax": "codeFence",
        "language": "md"
      }
    },
    {
      "type": "paragraph",
      "content": "",
      "children": [
        {
          "type": "text",
          "content": "Render default manuscript:"
        }
      ],
      "properties": {
        "sourceRange": {
          "lineStart": 173,
          "colStart": 1,
          "lineEnd": 173,
          "colEnd": 27
        },
        "sourceSyntax": "paragraph",
        "keepWithNext": true
      }
    },
    {
      "type": "code-block",
      "content": "npm run dev —prefix draft2final — samples/tutorial/manuscript.md —using mkd-manuscript —out samples/tutorial/manuscript.default.pdf",
      "properties": {
        "sourceRange": {
          "lineStart": 175,
          "colStart": 1,
          "lineEnd": 177,
          "colEnd": 4
        },
        "sourceSyntax": "codeFence",
        "language": "bash"
      }
    },
    {
      "type": "paragraph",
      "content": "",
      "children": [
        {
          "type": "text",
          "content": "What you should see:"
        }
      ],
      "properties": {
        "sourceRange": {
          "lineStart": 179,
          "colStart": 1,
          "lineEnd": 179,
          "colEnd": 21
        },
        "sourceSyntax": "paragraph",
        "keepWithNext": true
      }
    },
    {
      "type": "list-item-unordered-0",
      "content": "",
      "children": [
        {
          "type": "text",
          "content": "• "
        },
        {
          "type": "text",
          "content": "A manuscript-style PDF at "
        },
        {
          "type": "text",
          "content": "samples/tutorial/manuscript.default.pdf",
          "properties": {
            "style": {
              "fontFamily": "Cousine",
              "fontSize": 9.7,
              "color": "#173657",
              "backgroundColor": "#eef3f8",
              "borderRadius": 2
            }
          }
        }
      ],
      "properties": {
        "sourceRange": {
          "lineStart": 181,
          "colStart": 1,
          "lineEnd": 181,
          "colEnd": 70
        },
        "sourceSyntax": "listItem"
      }
    },
    {
      "type": "paragraph",
      "content": "",
      "children": [
        {
          "type": "text",
          "content": "Render classic manuscript:"
        }
      ],
      "properties": {
        "sourceRange": {
          "lineStart": 183,
          "colStart": 1,
          "lineEnd": 183,
          "colEnd": 27
        },
        "sourceSyntax": "paragraph",
        "keepWithNext": true
      }
    },
    {
      "type": "code-block",
      "content": "npm run dev —prefix draft2final — samples/tutorial/manuscript.md —using mkd-manuscript —theme classic —out samples/tutorial/manuscript.classic.pdf",
      "properties": {
        "sourceRange": {
          "lineStart": 185,
          "colStart": 1,
          "lineEnd": 187,
          "colEnd": 4
        },
        "sourceSyntax": "codeFence",
        "language": "bash"
      }
    },
    {
      "type": "paragraph",
      "content": "",
      "children": [
        {
          "type": "text",
          "content": "Now you have a writer-friendly workflow without giving up plain Markdown."
        }
      ],
      "properties": {
        "sourceRange": {
          "lineStart": 189,
          "colStart": 1,
          "lineEnd": 189,
          "colEnd": 74
        },
        "sourceSyntax": "paragraph"
      }
    },
    {
      "type": "paragraph",
      "content": "",
      "children": [
        {
          "type": "text",
          "content": "For writers, this is the relief point: you can stay in creative mode and still deliver industry-shaped output when it counts."
        }
      ],
      "properties": {
        "sourceRange": {
          "lineStart": 191,
          "colStart": 1,
          "lineEnd": 191,
          "colEnd": 126
        },
        "sourceSyntax": "paragraph"
      }
    },
    {
      "type": "heading-2",
      "content": "",
      "children": [
        {
          "type": "text",
          "content": "Part 4: Remix Mode (Because We Can)"
        }
      ],
      "properties": {
        "sourceRange": {
          "lineStart": 193,
          "colStart": 1,
          "lineEnd": 193,
          "colEnd": 39
        },
        "sourceSyntax": "h2"
      }
    },
    {
      "type": "paragraph",
      "content": "",
      "children": [
        {
          "type": "text",
          "content": "This is where people realize the bigger idea."
        }
      ],
      "properties": {
        "sourceRange": {
          "lineStart": 195,
          "colStart": 1,
          "lineEnd": 195,
          "colEnd": 46
        },
        "sourceSyntax": "paragraph"
      }
    },
    {
      "type": "paragraph",
      "content": "",
      "children": [
        {
          "type": "text",
          "content": "Technical manual as screenplay:"
        }
      ],
      "properties": {
        "sourceRange": {
          "lineStart": 197,
          "colStart": 1,
          "lineEnd": 197,
          "colEnd": 32
        },
        "sourceSyntax": "paragraph",
        "keepWithNext": true
      }
    },
    {
      "type": "code-block",
      "content": "npm run dev —prefix draft2final — samples/tutorial/tech-manual.md —using mkd-screenplay —out samples/tutorial/tech-manual.as-screenplay.pdf",
      "properties": {
        "sourceRange": {
          "lineStart": 199,
          "colStart": 1,
          "lineEnd": 201,
          "colEnd": 4
        },
        "sourceSyntax": "codeFence",
        "language": "bash"
      }
    },
    {
      "type": "paragraph",
      "content": "",
      "children": [
        {
          "type": "text",
          "content": "Screenplay as manuscript:"
        }
      ],
      "properties": {
        "sourceRange": {
          "lineStart": 203,
          "colStart": 1,
          "lineEnd": 203,
          "colEnd": 26
        },
        "sourceSyntax": "paragraph",
        "keepWithNext": true
      }
    },
    {
      "type": "code-block",
      "content": "npm run dev —prefix draft2final — samples/tutorial/screenplay.md —using mkd-manuscript —out samples/tutorial/screenplay.as-manuscript.pdf",
      "properties": {
        "sourceRange": {
          "lineStart": 205,
          "colStart": 1,
          "lineEnd": 207,
          "colEnd": 4
        },
        "sourceSyntax": "codeFence",
        "language": "bash"
      }
    },
    {
      "type": "paragraph",
      "content": "",
      "children": [
        {
          "type": "text",
          "content": "Manuscript as opensource-style markdown:"
        }
      ],
      "properties": {
        "sourceRange": {
          "lineStart": 209,
          "colStart": 1,
          "lineEnd": 209,
          "colEnd": 41
        },
        "sourceSyntax": "paragraph",
        "keepWithNext": true
      }
    },
    {
      "type": "code-block",
      "content": "npm run dev —prefix draft2final — samples/tutorial/manuscript.md —using mkd-mkd —theme opensource —out samples/tutorial/manuscript.as-opensource.pdf",
      "properties": {
        "sourceRange": {
          "lineStart": 211,
          "colStart": 1,
          "lineEnd": 213,
          "colEnd": 4
        },
        "sourceSyntax": "codeFence",
        "language": "bash"
      }
    },
    {
      "type": "paragraph",
      "content": "",
      "children": [
        {
          "type": "text",
          "content": "It is a little ridiculous. It is also genuinely useful when exploring tone and presentation quickly."
        }
      ],
      "properties": {
        "sourceRange": {
          "lineStart": 215,
          "colStart": 1,
          "lineEnd": 215,
          "colEnd": 101
        },
        "sourceSyntax": "paragraph"
      }
    },
    {
      "type": "paragraph",
      "content": "",
      "children": [
        {
          "type": "text",
          "content": "It also proves the core concept: source and output style do not have to be trapped together."
        }
      ],
      "properties": {
        "sourceRange": {
          "lineStart": 217,
          "colStart": 1,
          "lineEnd": 217,
          "colEnd": 93
        },
        "sourceSyntax": "paragraph"
      }
    },
    {
      "type": "heading-2",
      "content": "",
      "children": [
        {
          "type": "text",
          "content": "Part 5: Peek Under the Hood (Optional)"
        }
      ],
      "properties": {
        "sourceRange": {
          "lineStart": 219,
          "colStart": 1,
          "lineEnd": 219,
          "colEnd": 42
        },
        "sourceSyntax": "h2"
      }
    },
    {
      "type": "paragraph",
      "content": "",
      "children": [
        {
          "type": "text",
          "content": "Want the transmuted document structure instead of a PDF?"
        }
      ],
      "properties": {
        "sourceRange": {
          "lineStart": 221,
          "colStart": 1,
          "lineEnd": 221,
          "colEnd": 57
        },
        "sourceSyntax": "paragraph"
      }
    },
    {
      "type": "code-block",
      "content": "npm run dev —prefix draft2final — samples/tutorial/tech-manual.md —using mkd-mkd —out samples/tutorial/tech-manual.ast.json",
      "properties": {
        "sourceRange": {
          "lineStart": 223,
          "colStart": 1,
          "lineEnd": 225,
          "colEnd": 4
        },
        "sourceSyntax": "codeFence",
        "language": "bash"
      }
    },
    {
      "type": "paragraph",
      "content": "",
      "children": [
        {
          "type": "text",
          "content": "If output ends with "
        },
        {
          "type": "text",
          "content": ".json",
          "properties": {
            "style": {
              "fontFamily": "Cousine",
              "fontSize": 9.7,
              "color": "#173657",
              "backgroundColor": "#eef3f8",
              "borderRadius": 2
            }
          }
        },
        {
          "type": "text",
          "content": ", "
        },
        {
          "type": "text",
          "content": "draft2final",
          "properties": {
            "style": {
              "fontFamily": "Cousine",
              "fontSize": 9.7,
              "color": "#173657",
              "backgroundColor": "#eef3f8",
              "borderRadius": 2
            }
          }
        },
        {
          "type": "text",
          "content": " writes VMPrint "
        },
        {
          "type": "text",
          "content": "DocumentInput",
          "properties": {
            "style": {
              "fontFamily": "Cousine",
              "fontSize": 9.7,
              "color": "#173657",
              "backgroundColor": "#eef3f8",
              "borderRadius": 2
            }
          }
        },
        {
          "type": "text",
          "content": " AST JSON."
        }
      ],
      "properties": {
        "sourceRange": {
          "lineStart": 227,
          "colStart": 1,
          "lineEnd": 227,
          "colEnd": 84
        },
        "sourceSyntax": "paragraph"
      }
    },
    {
      "type": "heading-2",
      "content": "",
      "children": [
        {
          "type": "text",
          "content": "Part 6: Let Frontmatter Do the Work"
        }
      ],
      "properties": {
        "sourceRange": {
          "lineStart": 229,
          "colStart": 1,
          "lineEnd": 229,
          "colEnd": 39
        },
        "sourceSyntax": "h2"
      }
    },
    {
      "type": "paragraph",
      "content": "",
      "children": [
        {
          "type": "text",
          "content": "Add this to the top of any "
        },
        {
          "type": "text",
          "content": ".md",
          "properties": {
            "style": {
              "fontFamily": "Cousine",
              "fontSize": 9.7,
              "color": "#173657",
              "backgroundColor": "#eef3f8",
              "borderRadius": 2
            }
          }
        },
        {
          "type": "text",
          "content": " file:"
        }
      ],
      "properties": {
        "sourceRange": {
          "lineStart": 231,
          "colStart": 1,
          "lineEnd": 231,
          "colEnd": 39
        },
        "sourceSyntax": "paragraph",
        "keepWithNext": true
      }
    },
    {
      "type": "code-block",
      "content": "—\nusing: mkd-manuscript\ntheme: classic\n—",
      "properties": {
        "sourceRange": {
          "lineStart": 233,
          "colStart": 1,
          "lineEnd": 238,
          "colEnd": 4
        },
        "sourceSyntax": "codeFence",
        "language": "md"
      }
    },
    {
      "type": "paragraph",
      "content": "",
      "children": [
        {
          "type": "text",
          "content": "Then run:"
        }
      ],
      "properties": {
        "sourceRange": {
          "lineStart": 240,
          "colStart": 1,
          "lineEnd": 240,
          "colEnd": 10
        },
        "sourceSyntax": "paragraph",
        "keepWithNext": true
      }
    },
    {
      "type": "code-block",
      "content": "npm run dev —prefix draft2final — samples/tutorial/manuscript.md —out samples/tutorial/manuscript.auto.pdf",
      "properties": {
        "sourceRange": {
          "lineStart": 242,
          "colStart": 1,
          "lineEnd": 244,
          "colEnd": 4
        },
        "sourceSyntax": "codeFence",
        "language": "bash"
      }
    },
    {
      "type": "paragraph",
      "content": "",
      "children": [
        {
          "type": "text",
          "content": "No "
        },
        {
          "type": "text",
          "content": "--using",
          "properties": {
            "style": {
              "fontFamily": "Cousine",
              "fontSize": 9.7,
              "color": "#173657",
              "backgroundColor": "#eef3f8",
              "borderRadius": 2
            }
          }
        },
        {
          "type": "text",
          "content": " needed."
        }
      ],
      "properties": {
        "sourceRange": {
          "lineStart": 246,
          "colStart": 1,
          "lineEnd": 246,
          "colEnd": 21
        },
        "sourceSyntax": "paragraph"
      }
    },
    {
      "type": "paragraph",
      "content": "",
      "children": [
        {
          "type": "text",
          "content": "What you should see:"
        }
      ],
      "properties": {
        "sourceRange": {
          "lineStart": 248,
          "colStart": 1,
          "lineEnd": 248,
          "colEnd": 21
        },
        "sourceSyntax": "paragraph",
        "keepWithNext": true
      }
    },
    {
      "type": "list-item-unordered-0",
      "content": "",
      "children": [
        {
          "type": "text",
          "content": "• "
        },
        {
          "type": "text",
          "content": "draft2final",
          "properties": {
            "style": {
              "fontFamily": "Cousine",
              "fontSize": 9.7,
              "color": "#173657",
              "backgroundColor": "#eef3f8",
              "borderRadius": 2
            }
          }
        },
        {
          "type": "text",
          "content": " infers the transmuter from frontmatter and writes the PDF"
        }
      ],
      "properties": {
        "sourceRange": {
          "lineStart": 250,
          "colStart": 1,
          "lineEnd": 250,
          "colEnd": 74
        },
        "sourceSyntax": "listItem"
      }
    },
    {
      "type": "heading-2",
      "content": "",
      "children": [
        {
          "type": "text",
          "content": "Quick Mental Model"
        }
      ],
      "properties": {
        "sourceRange": {
          "lineStart": 252,
          "colStart": 1,
          "lineEnd": 252,
          "colEnd": 22
        },
        "sourceSyntax": "h2"
      }
    },
    {
      "type": "list-item-unordered-0",
      "content": "",
      "children": [
        {
          "type": "text",
          "content": "• "
        },
        {
          "type": "text",
          "content": "You write Markdown"
        }
      ],
      "properties": {
        "sourceRange": {
          "lineStart": 254,
          "colStart": 1,
          "lineEnd": 254,
          "colEnd": 21
        },
        "sourceSyntax": "listItem"
      }
    },
    {
      "type": "list-item-unordered-0",
      "content": "",
      "children": [
        {
          "type": "text",
          "content": "• "
        },
        {
          "type": "text",
          "content": "A transmuter interprets intent ("
        },
        {
          "type": "text",
          "content": "mkd-mkd",
          "properties": {
            "style": {
              "fontFamily": "Cousine",
              "fontSize": 9.7,
              "color": "#173657",
              "backgroundColor": "#eef3f8",
              "borderRadius": 2
            }
          }
        },
        {
          "type": "text",
          "content": ", "
        },
        {
          "type": "text",
          "content": "mkd-screenplay",
          "properties": {
            "style": {
              "fontFamily": "Cousine",
              "fontSize": 9.7,
              "color": "#173657",
              "backgroundColor": "#eef3f8",
              "borderRadius": 2
            }
          }
        },
        {
          "type": "text",
          "content": ", "
        },
        {
          "type": "text",
          "content": "mkd-manuscript",
          "properties": {
            "style": {
              "fontFamily": "Cousine",
              "fontSize": 9.7,
              "color": "#173657",
              "backgroundColor": "#eef3f8",
              "borderRadius": 2
            }
          }
        },
        {
          "type": "text",
          "content": ", etc.)"
        }
      ],
      "properties": {
        "sourceRange": {
          "lineStart": 255,
          "colStart": 1,
          "lineEnd": 255,
          "colEnd": 87
        },
        "sourceSyntax": "listItem"
      }
    },
    {
      "type": "list-item-unordered-0",
      "content": "",
      "children": [
        {
          "type": "text",
          "content": "• "
        },
        {
          "type": "text",
          "content": "draft2final",
          "properties": {
            "style": {
              "fontFamily": "Cousine",
              "fontSize": 9.7,
              "color": "#173657",
              "backgroundColor": "#eef3f8",
              "borderRadius": 2
            }
          }
        },
        {
          "type": "text",
          "content": " renders polished output"
        }
      ],
      "properties": {
        "sourceRange": {
          "lineStart": 256,
          "colStart": 1,
          "lineEnd": 256,
          "colEnd": 40
        },
        "sourceSyntax": "listItem"
      }
    },
    {
      "type": "paragraph",
      "content": "",
      "children": [
        {
          "type": "text",
          "content": "Same source. Different destination."
        }
      ],
      "properties": {
        "sourceRange": {
          "lineStart": 258,
          "colStart": 1,
          "lineEnd": 258,
          "colEnd": 36
        },
        "sourceSyntax": "paragraph"
      }
    },
    {
      "type": "paragraph",
      "content": "",
      "children": [
        {
          "type": "text",
          "content": "This is the promise: write once, publish many ways."
        }
      ],
      "properties": {
        "sourceRange": {
          "lineStart": 260,
          "colStart": 1,
          "lineEnd": 260,
          "colEnd": 52
        },
        "sourceSyntax": "paragraph"
      }
    },
    {
      "type": "heading-2",
      "content": "",
      "children": [
        {
          "type": "text",
          "content": "Where Theme and Config Files Live"
        }
      ],
      "properties": {
        "sourceRange": {
          "lineStart": 262,
          "colStart": 1,
          "lineEnd": 262,
          "colEnd": 37
        },
        "sourceSyntax": "h2"
      }
    },
    {
      "type": "list-item-unordered-0",
      "content": "",
      "children": [
        {
          "type": "text",
          "content": "• "
        },
        {
          "type": "text",
          "content": "Default config: "
        },
        {
          "type": "text",
          "content": "draft2final/config/<using>.config.yaml",
          "properties": {
            "style": {
              "fontFamily": "Cousine",
              "fontSize": 9.7,
              "color": "#173657",
              "backgroundColor": "#eef3f8",
              "borderRadius": 2
            }
          }
        }
      ],
      "properties": {
        "sourceRange": {
          "lineStart": 264,
          "colStart": 1,
          "lineEnd": 264,
          "colEnd": 59
        },
        "sourceSyntax": "listItem"
      }
    },
    {
      "type": "list-item-unordered-0",
      "content": "",
      "children": [
        {
          "type": "text",
          "content": "• "
        },
        {
          "type": "text",
          "content": "Named themes: "
        },
        {
          "type": "text",
          "content": "draft2final/themes/<using>/<name>.yaml",
          "properties": {
            "style": {
              "fontFamily": "Cousine",
              "fontSize": 9.7,
              "color": "#173657",
              "backgroundColor": "#eef3f8",
              "borderRadius": 2
            }
          }
        }
      ],
      "properties": {
        "sourceRange": {
          "lineStart": 265,
          "colStart": 1,
          "lineEnd": 265,
          "colEnd": 57
        },
        "sourceSyntax": "listItem"
      }
    },
    {
      "type": "list-item-unordered-0",
      "content": "",
      "children": [
        {
          "type": "text",
          "content": "• "
        },
        {
          "type": "text",
          "content": "You can pass file paths directly with "
        },
        {
          "type": "text",
          "content": "--config",
          "properties": {
            "style": {
              "fontFamily": "Cousine",
              "fontSize": 9.7,
              "color": "#173657",
              "backgroundColor": "#eef3f8",
              "borderRadius": 2
            }
          }
        },
        {
          "type": "text",
          "content": " and "
        },
        {
          "type": "text",
          "content": "--theme",
          "properties": {
            "style": {
              "fontFamily": "Cousine",
              "fontSize": 9.7,
              "color": "#173657",
              "backgroundColor": "#eef3f8",
              "borderRadius": 2
            }
          }
        }
      ],
      "properties": {
        "sourceRange": {
          "lineStart": 266,
          "colStart": 1,
          "lineEnd": 266,
          "colEnd": 65
        },
        "sourceSyntax": "listItem"
      }
    },
    {
      "type": "heading-2",
      "content": "",
      "children": [
        {
          "type": "text",
          "content": "Try This Next"
        }
      ],
      "properties": {
        "sourceRange": {
          "lineStart": 268,
          "colStart": 1,
          "lineEnd": 268,
          "colEnd": 17
        },
        "sourceSyntax": "h2"
      }
    },
    {
      "type": "list-item-ordered-0",
      "content": "",
      "children": [
        {
          "type": "text",
          "content": "I.  "
        },
        {
          "type": "text",
          "content": "Pick one real piece of your writing and generate 3 output styles."
        }
      ],
      "properties": {
        "sourceRange": {
          "lineStart": 270,
          "colStart": 1,
          "lineEnd": 270,
          "colEnd": 69
        },
        "sourceSyntax": "listItem"
      }
    },
    {
      "type": "list-item-ordered-0",
      "content": "",
      "children": [
        {
          "type": "text",
          "content": "II.  "
        },
        {
          "type": "text",
          "content": "Share all 3 PDFs with a collaborator and ask which feels right for the audience."
        }
      ],
      "properties": {
        "sourceRange": {
          "lineStart": 271,
          "colStart": 1,
          "lineEnd": 271,
          "colEnd": 84
        },
        "sourceSyntax": "listItem"
      }
    },
    {
      "type": "list-item-ordered-0",
      "content": "",
      "children": [
        {
          "type": "text",
          "content": "III.  "
        },
        {
          "type": "text",
          "content": "Keep writing in plain Markdown and stop worrying about format lock-in."
        }
      ],
      "properties": {
        "sourceRange": {
          "lineStart": 272,
          "colStart": 1,
          "lineEnd": 272,
          "colEnd": 74
        },
        "sourceSyntax": "listItem"
      }
    },
    {
      "type": "paragraph",
      "content": "",
      "children": [
        {
          "type": "text",
          "content": "If this tutorial saved you from one “wrong format” submission scare, it already paid for itself."
        }
      ],
      "properties": {
        "sourceRange": {
          "lineStart": 274,
          "colStart": 1,
          "lineEnd": 274,
          "colEnd": 97
        },
        "sourceSyntax": "paragraph"
      }
    }
  ],
  "header": {
    "default": {
      "elements": [
        {
          "type": "paragraph",
          "content": "draft2final Tutorial",
          "properties": {
            "style": {
              "textAlign": "center",
              "fontFamily": "Carlito",
              "fontSize": 8.6,
              "color": "#7f8b9c",
              "letterSpacing": 0.9,
              "marginTop": -20,
              "marginBottom": 7
            }
          }
        }
      ]
    }
  },
  "footer": {
    "default": {
      "elements": [
        {
          "type": "paragraph",
          "content": "Page {pageNumber}",
          "properties": {
            "style": {
              "textAlign": "center",
              "fontFamily": "Carlito",
              "fontSize": 8.7,
              "color": "#8a93a1",
              "marginTop": 26
            }
          }
        }
      ]
    }
  }
}